Metadata-Version: 2.4
Name: llm-tools-memory
Version: 0.1.1
Summary: Memory tools for LLM
Author: Tom Bedor
License-Expression: Apache-2.0
Project-URL: Homepage, https://github.com/tombedor/llm-tools-memory
Project-URL: Changelog, https://github.com/tombedor/llm-tools-memory/releases
Project-URL: Issues, https://github.com/tombedor/llm-tools-memory/issues
Project-URL: CI, https://github.com/tombedor/llm-tools-memory/actions
Requires-Python: >=3.9
License-File: LICENSE
Requires-Dist: llm>=0.26
Provides-Extra: test
Requires-Dist: pytest; extra == "test"
Requires-Dist: llm-echo>=0.3a1; extra == "test"
Dynamic: license-file
